.gitignore
.travis.yml
ChangeLog.rst
LICENSE
MANIFEST.in
README.rst
pytest.ini
requirements.txt
setup.cfg
setup.py
test
test-requirements.txt
ycfg
test/context.py
test/data
test/test_collections.py
test/test_config_file.py
test/data/empty.yaml
test/data/expected
test/data/not-a-dict.yaml
test/data/ordering-test.yaml
test/data/expected/config_file_tester
test/data/expected/folded_keys_ordered_dict_tester
test/data/expected/folded_keys_value_dict_pair_tester
test/data/expected/config_file_tester/ordering_test.out
test/data/expected/config_file_tester/sample_test.out
test/data/expected/folded_keys_ordered_dict_tester/assign_test_1.out
test/data/expected/folded_keys_value_dict_pair_tester/assign_test_1.out
ycfg/__init__.py
ycfg/collections.py
ycfg/config_file.py
ycfg/version.py
ycfg/yaml.py
ycfg.egg-info/PKG-INFO
ycfg.egg-info/SOURCES.txt
ycfg.egg-info/dependency_links.txt
ycfg.egg-info/requires.txt
ycfg.egg-info/top_level.txt
ycfg.egg-info/zip-safe