Metadata-Version: 1.1
Name: ycfg
Version: 0.2.0
Summary: Easy way to get and access configuration data from YAML files
Home-page: https://github.com/zaufi/trivial-yaml-config
Author: Alex Turbov
Author-email: I.zaufi@gmail.com
License: GNU General Public License v3 or later (GPLv3+)
Download-URL: https://github.com/zaufi/trivial-yaml-config/archive/release/0.2.0.tar.gz
Platform: UNKNOWN
Classifier: Development Status :: 4 - Beta
Classifier: Intended Audience :: Developers
Classifier: License :: OSI Approved :: GNU General Public License v3 or later (GPLv3+)
Classifier: Natural Language :: English
Classifier: Programming Language :: Python :: 3
